{
    "sites": [
        {
            "name": "低端影视",
            "type": 3,
            "api": "csp_Ddrk"
        },
        {
            "name": "厂长资源",
            "type": 3,
            "api": "csp_Czsapp"
        },
        {
            "name": "绝缘影视",
            "type": 3,
            "api": "csp_Bdys"
        },
        {
            "name": "欧乐影院",
            "type": 3,
            "api": "csp_Olevod"
        },
        {
            "name": "独播库",
            "type": 3,
            "api": "csp_duboku"
        },
        {
            "name": "在线之家",
            "type": 3,
            "api": "csp_Zxzj"
        },
        {
            "name": "LIBVIO",
            "type": 3,
            "api": "csp_libvio"
        },
        {
            "name": "AGE动漫",
            "type": 3,
            "api": "csp_age"
        },
        {
            "name": "ギリギリ动漫",
            "type": 3,
            "api": "csp_girlgirllove"
        }
    ]
}
